bridgtl_edm_dp_python_library/__init__.py
bridgtl_edm_dp_python_library/common/__init__.py
bridgtl_edm_dp_python_library/data_platform/__init__.py
bridgtl_edm_dp_python_library/data_platform/connection/__init__.py
bridgtl_edm_dp_python_library/data_platform/connection/models.py
bridgtl_edm_dp_python_library/data_platform/pyspark/__init__.py
bridgtl_edm_dp_python_library/data_platform/pyspark/bigquery/__init__.py
bridgtl_edm_dp_python_library/data_platform/pyspark/JupyterKubernetesSparkSession.py
bridgtl_edm_dp_python_library/data_platform/pyspark/KubernetesSparkSession.py
bridgtl_edm_dp_python_library/data_platform/temporal/__init__.py
bridgtl_edm_dp_python_library-0.1.30.dist-info/METADATA
bridgtl_edm_dp_python_library-0.1.30.dist-info/WHEEL
bridgtl_edm_dp_python_library-0.1.30.dist-info/RECORD
